fabienpendu_lib/SF-clairon.wav
fabienpendu_lib/__init__.py
fabienpendu_lib/applaudissement.wav
fabienpendu_lib/buzzer_perdu.wav
fabienpendu_lib/core.py
fabienpendu_lib/coup_ventre.wav
fabienpendu_lib/dico_anglais.txt
fabienpendu_lib/dico_mots_simple.txt
fabienpendu_lib/pendu.gif
fabienpendu_lib/pendu_0.gif
fabienpendu_lib/pendu_1.gif
fabienpendu_lib/pendu_2.gif
fabienpendu_lib/pendu_3.gif
fabienpendu_lib/pendu_4.gif
fabienpendu_lib/pendu_5.gif
fabienpendu_lib/pendu_6.gif
fabienpendu_lib/pendu_6_1.gif
fabienpendu_lib/pendu_6_2.gif
fabienpendu_lib/pendu_cool.gif
fabienpendu_lib/sf-os-nuque-briser-05.wav
fabienpendu_lib/sf_cri_surprise_femme.wav
fabienpendu_lib/sf_grincements_bois_01.wav
fabienpendu_lib/sf_grincements_bois_02.wav
fabienpendu_lib/souffle_air.wav
fabienpendu_lib/touche_clavier.wav
fabienpendu_lib/vindication.wav
fabienpendu-0.2.6.dist-info/METADATA
fabienpendu-0.2.6.dist-info/WHEEL
fabienpendu-0.2.6.dist-info/entry_points.txt
fabienpendu-0.2.6.dist-info/top_level.txt
fabienpendu-0.2.6.dist-info/RECORD
